Metadata-Version: 1.1
Name: fieldy
Version: 0.5.0
Summary: Lib to help structure objects from jsons
Home-page: https://github.com/NeverDefineUs/fieldy
Author: arthurlpgc
Author-email: arthurlpgc@gmail.com
License: MIT
Download-URL: https://github.com/NeverDefineUs/fieldy/archive/0.5.0.tar.gz
Keywords: SOME,MEANINGFULL,KEYWORDS
Platform: UNKNOWN
Classifier: Development Status :: 3 - Alpha
Classifier: Intended Audience :: Developers
Classifier: Topic :: Software Development :: Build Tools
Classifier: License :: OSI Approved :: MIT License
Classifier: Programming Language :: Python :: 3
Classifier: Programming Language :: Python :: 3.4
Classifier: Programming Language :: Python :: 3.5
Classifier: Programming Language :: Python :: 3.6
